cmselemental/__init__.py
cmselemental/_version.py
cmselemental/cmselemental.py
cmselemental/extras.py
cmselemental/testing.py
cmselemental/types.py
cmselemental/data/README.md
cmselemental/data/look_and_say.dat
cmselemental/models/__init__.py
cmselemental/models/base.py
cmselemental/models/common.py
cmselemental/models/procedures.py
cmselemental/tests/__init__.py
cmselemental/tests/test_cmselemental.py
cmselemental/tests/test_hdf.py
cmselemental/tests/test_models.py
cmselemental/tests/test_models_qc.py
cmselemental/tests/test_utils.py
cmselemental/util/__init__.py
cmselemental/util/autodocs.py
cmselemental/util/decorators.py
cmselemental/util/exceptions.py
cmselemental/util/hdf.py
cmselemental/util/importing.py
cmselemental/util/serialization.py
cmselemental-0.2.0.dist-info/LICENSE
cmselemental-0.2.0.dist-info/METADATA
cmselemental-0.2.0.dist-info/WHEEL
cmselemental-0.2.0.dist-info/top_level.txt
cmselemental-0.2.0.dist-info/RECORD
