Metadata-Version: 2.1
Name: cmselemental
Version: 0.2.0
Summary: UNKNOWN
Home-page: UNKNOWN
Author: MolSSI
Author-email: support@molssi.org
License: BSD-3-Clause
Platform: UNKNOWN
Classifier: Development Status :: 3 - Alpha
License-File: LICENSE
Requires-Dist: numpy
Requires-Dist: pydantic
Provides-Extra: hdf5
Requires-Dist: h5py ; extra == 'hdf5'
Requires-Dist: h5json ; extra == 'hdf5'
Provides-Extra: msgpack
Requires-Dist: msgpack ; extra == 'msgpack'
Provides-Extra: tests
Requires-Dist: pytest (>=4.0.0) ; extra == 'tests'
Requires-Dist: pytest-cov ; extra == 'tests'
Provides-Extra: yaml
Requires-Dist: pyyaml ; extra == 'yaml'
